{"Return": {"@xmlns": "http://www.irs.gov/efile", "@xmlns:xsi": "http://www.w3.org/2001/XMLSchema-instance", "@returnVersion": "2012v2.3", "ReturnHeader": {"@binaryAttachmentCount": "0", "Timestamp": "2013-11-15T17:07:11-06:00", "TaxPeriodEndDate": "2012-12-31", "PreparerFirm": {"PreparerFirmBusinessName": {"BusinessNameLine1": "CPA GROUP OF LARAMIE LLC"}, "PreparerFirmUSAddress": {"AddressLine1": "1273 N 15TH ST SUITE 121", "City": "LARAMIE", "State": "WY", "ZIPCode": "82072"}}, "ReturnType": "990", "TaxPeriodBeginDate": "2012-01-01", "Filer": {"EIN": "841236806", "Name": {"BusinessNameLine1": "NORTH PARK MEDICAL CLINIC INC"}, "NameControl": "NORT", "Phone": "9707234255", "USAddress": {"AddressLine1": "P O BOX 686", "City": "WALDEN", "State": "CO", "ZIPCode": "80480"}}, "Officer": {"Name": "DOYLE JENKINS", "Title": "PRESIDENT", "Phone": "9707234255", "DateSigned": "2013-11-15", "AuthorizeThirdParty": "true"}, "Preparer": {"Name": "JENNIFER K BROOK", "Phone": "3077457241", "DatePrepared": "2013-11-15"}, "TaxYear": "2012", "BuildTS": "2016-02-25 16:41:14Z"}, "ReturnData": {"@documentCount": "4", "IRS990": {"@documentId": "RetDoc4", "@referenceDocumentId": "RetDoc5", "NameOfPrincipalOfficerPerson": "DUKE BEHRENS", "AddressPrincipalOfficerUS": {"AddressLine1": "P O BOX 686", "City": "WALDEN", "State": "CO", "ZIPCode": "80480"}, "GrossReceipts": "261747", "GroupReturnForAffiliates": "false", "Organization501c3": "X", "TypeOfOrganizationCorporation": "X", "YearFormation": "1992", "StateLegalDomicile": "CO", "ActivityOrMissionDescription": "PROVIDE MEDICAL CARE IN A RURAL AREA", "NbrVotingMembersGoverningBody": "7", "NbrIndependentVotingMembers": "7", "TotalNbrEmployees": "12", "TotalNbrVolunteers": "10", "TotalGrossUBI": "0", "ContributionsGrantsPriorYear": "7555", "ContributionsGrantsCurrentYear": "107600", "ProgramServiceRevenuePriorYear": "352400", "ProgramServiceRevenueCY": "153499", "InvestmentIncomePriorYear": "3803", "InvestmentIncomeCurrentYear": "648", "OtherRevenuePriorYear": "43029", "OtherRevenueCurrentYear": "0", "TotalRevenuePriorYear": "406787", "TotalRevenueCurrentYear": "261747", "GrantsAndSimilarAmntsCY": "0", "BenefitsPaidToMembersCY": "0", "SalariesEtcPriorYear": "204370", "SalariesEtcCurrentYear": "32153", "TotalProfFundrsngExpCY": "0", "TotalFundrsngExpCurrentYear": "0", "OtherExpensePriorYear": "299381", "OtherExpensesCurrentYear": "252282", "TotalExpensesPriorYear": "503751", "TotalExpensesCurrentYear": "284435", "RevenuesLessExpensesPriorYear": "-96964", "RevenuesLessExpensesCY": "-22688", "TotalAssetsBOY": "2450089", "TotalAssetsEOY": "2364125", "TotalLiabilitiesBOY": "355675", "TotalLiabilitiesEOY": "347156", "NetAssetsOrFundBalancesBOY": "2094414", "NetAssetsOrFundBalancesEOY": "2016969", "MissionDescription": "PROVIDE MEDICAL CARE IN A RURAL AREA", "SignificantNewProgramServices": "false", "SignificantChange": "false", "Expense": "275898", "Description": "MEDICAL SERVICES PROVIDED FOR A RURAL COMMUNITY OF 1500 RESIDENTS", "TotalProgramServiceExpense": "275898", "DescribedIn501C3": {"@referenceDocumentId": "RetDoc2", "#text": "true"}, "ScheduleBRequired": "false", "PoliticalActivities": "false", "LobbyingActivities": "false", "SubjectToProxyTax": "false", "DonorAdvisedFunds": {"@referenceDocumentId": "RetDoc3", "#text": "false"}, "ConservationEasements": {"@referenceDocumentId": "RetDoc3", "#text": "false"}, "CollectionsOfArt": {"@referenceDocumentId": "RetDoc3", "#text": "false"}, "CreditCounseling": {"@referenceDocumentId": "RetDoc3", "#text": "false"}, "TermOrPermanentEndowments": {"@referenceDocumentId": "RetDoc3", "#text": "false"}, "ReportLandBldgEquip": {"@referenceDocumentId": "RetDoc3", "#text": "true"}, "ReportInvestOthSecurities": {"@referenceDocumentId": "RetDoc3", "#text": "false"}, "ReportProgRelInvest": {"@referenceDocumentId": "RetDoc3", "#text": "false"}, "ReportOtherAssets": {"@referenceDocumentId": "RetDoc3", "#text": "false"}, "ReportOtherLiabilities": {"@referenceDocumentId": "RetDoc3", "#text": "true"}, "ReportFin48Footnote": {"@referenceDocumentId": "RetDoc3", "#text": "false"}, "IndependentAuditFinancialStmt": {"@referenceDocumentId": "RetDoc3", "#text": "false"}, "ConsolidatedAuditFinancialStmt": {"@referenceDocumentId": "RetDoc3", "#text": "false"}, "School": "false", "ForeignOffice": "false", "ForeignActivities": "false", "MoreThan5000KToOrganizations": "false", "MoreThan5000KToIndividuals": "false", "ProfessionalFundraising": "false", "FundraisingActivities": "false", "Gaming": "false", "Hospital": "false", "GrantsToOrganizations": "false", "GrantsToIndividuals": "false", "ScheduleJRequired": "false", "TaxExemptBonds": "false", "ExcessBenefitTransaction": "false", "PriorExcessBenefitTransaction": "false", "LoanToOfficerOrDQP": "false", "GrantToRelatedPerson": "false", "BsnssRltnshpWithOrganization": "false", "BsnssRltnshpThruFamilyMember": "false", "OfficerEntityWithBsnssRltnshp": "false", "DeductibleNonCashContributions": "false", "DeductibleContributionsOfArt": "false", "Terminated": "false", "PartialLiquidation": "false", "DisregardedEntity": "false", "RelatedEntity": "false", "RelatedOrgControlledEntity": "false", "TransfersToExemptNonChrtblOrg": "false", "ActivitiesConductedPartnership": "false", "ScheduleORequired": "true", "NumberFormsTransmittedWith1096": "3", "NumberW2GIncluded": "0", "NumberOfEmployees": "12", "EmploymentTaxReturnsFiled": "true", "UnrelatedBusinessIncome": "false", "ForeignFinancialAccount": "false", "ProhibitedTaxShelterTrans": "false", "TaxablePartyNotification": "false", "NonDeductibleContributions": "false", "IndoorTanningServices": "false", "InfoInScheduleOPartVI": "X", "NbrVotingGoverningBodyMembers": "7", "NumberIndependentVotingMembers": "7", "FamilyOrBusinessRelationship": "false", "DelegationOfManagementDuties": "false", "ChangesToOrganizingDocs": "false", "MaterialDiversionOrMisuse": "false", "MembersOrStockholders": "false", "ElectionOfBoardMembers": "false", "DecisionsSubjectToApproval": "false", "MinutesOfGoverningBody": "true", "MinutesOfCommittees": "true", "OfficerMailingAddress": "false", "LocalChapters": "false", "Form990ProvidedToGoverningBody": "true", "ConflictOfInterestPolicy": "true", "AnnualDisclosureCoveredPersons": "false", "RegularMonitoringEnforcement": "false", "WhistleblowerPolicy": "false", "DocumentRetentionPolicy": "false", "CompensationProcessCEO": "false", "CompensationProcessOther": "false", "InvestmentInJointVenture": "false", "UponRequest": "X", "TheBooksAreInCareOf": {"NamePerson": "DUKE BEHRENS", "TelephoneNumber": "9707238413", "AddressUS": {"AddressLine1": "P O BOX 686", "City": "WALDEN", "State": "CO", "ZIPCode": "80480"}}, "NoListedPersonsCompensated": "X", "Form990PartVIISectionA": [{"NamePerson": "BERT SCHILLING", "Title": "DIRECTOR", "AverageHoursPerWeek": "2.00", "IndividualTrusteeOrDirector": "X", "ReportableCompFromOrganization": "0", "ReportableCompFromRelatedOrgs": "0", "OtherCompensation": "0"}, {"NamePerson": "VALDON BEHERNS", "Title": "DIRECTOR", "AverageHoursPerWeek": "2.00", "IndividualTrusteeOrDirector": "X", "ReportableCompFromOrganization": "0", "ReportableCompFromRelatedOrgs": "0", "OtherCompensation": "0"}, {"NamePerson": "JEFF SCHIEDT", "Title": "DIRECTOR", "AverageHoursPerWeek": "2.00", "IndividualTrusteeOrDirector": "X", "ReportableCompFromOrganization": "0", "ReportableCompFromRelatedOrgs": "0", "OtherCompensation": "0"}, {"NamePerson": "DOYLE JENKINS", "Title": "PRESIDENT", "AverageHoursPerWeek": "4.00", "Officer": "X", "ReportableCompFromOrganization": "0", "ReportableCompFromRelatedOrgs": "0", "OtherCompensation": "0"}, {"NamePerson": "CHARLOTTE ANDERSON", "Title": "VICE PRESIDE", "AverageHoursPerWeek": "2.00", "Officer": "X", "ReportableCompFromOrganization": "0", "ReportableCompFromRelatedOrgs": "0", "OtherCompensation": "0"}, {"NamePerson": "ELIZABETH IRVINE", "Title": "TREASURER", "AverageHoursPerWeek": "4.00", "Officer": "X", "ReportableCompFromOrganization": "0", "ReportableCompFromRelatedOrgs": "0", "OtherCompensation": "0"}, {"NamePerson": "HELEN WILLIAMS", "Title": "SECRETARY", "AverageHoursPerWeek": "2.00", "Officer": "X", "ReportableCompFromOrganization": "0", "ReportableCompFromRelatedOrgs": "0", "OtherCompensation": "0"}], "FormersListed": "false", "TotalCompGT150K": "false", "CompensationFromOtherSources": "false", "GovernmentGrants": "107500", "AllOtherContributions": "100", "TotalContributions": "107600", "ProgramServiceRevenue": {"Description": "PROGRAM SERVICE REVENUE", "TotalRevenueColumn": "153499", "RelatedOrExemptFunctionIncome": "153499"}, "TotalProgramServiceRevenue": "153499", "InvestmentIncome": {"TotalRevenueColumn": "648", "ExclusionAmount": "648"}, "TotalRevenue": {"TotalRevenueColumn": "261747", "RelatedOrExemptFunctionIncome": "153499", "ExclusionAmount": "648"}, "InfoInScheduleOPartIX": "X", "OtherSalariesAndWages": {"Total": "27591", "ProgramServices": "27591"}, "OtherEmployeeBenefits": {"Total": "1701", "ProgramServices": "1701"}, "PayrollTaxes": {"Total": "2861", "ProgramServices": "2861"}, "FeesForServicesLegal": {"Total": "135", "ManagementAndGeneral": "135"}, "FeesForServicesOther": {"Total": "95922", "ProgramServices": "95922"}, "Advertising": {"Total": "191", "ProgramServices": "191"}, "OfficeExpenses": {"Total": "4505", "ProgramServices": "4505"}, "Occupancy": {"Total": "11929", "ProgramServices": "11929"}, "Travel": {"Total": "4941", "ProgramServices": "4941"}, "Interest": {"Total": "25280", "ProgramServices": "25280"}, "DepreciationDepletion": {"Total": "69320", "ProgramServices": "69320"}, "Insurance": {"Total": "7584", "ManagementAndGeneral": "7584"}, "OtherExpenses": [{"Description": "JANITORIAL EXPENSE", "Total": "12668", "ProgramServices": "12668"}, {"Description": "BUILDING MAINTENANCE", "Total": "8445", "ProgramServices": "8445"}, {"Description": "MISCELLANEOUS EXPENSES", "Total": "4067", "ProgramServices": "4067"}, {"Description": "EQUIPMENT MAINTENANCE", "Total": "2089", "ProgramServices": "2089"}], "AllOtherExpenses": {"Total": "5206", "ProgramServices": "4388", "ManagementAndGeneral": "818"}, "TotalFunctionalExpenses": {"Total": "284435", "ProgramServices": "275898", "ManagementAndGeneral": "8537", "Fundraising": "0"}, "CashNonInterestBearing": {"BOY": "23564", "EOY": "27700"}, "SavingsAndTempCashInvestments": {"BOY": "12956", "EOY": "61743"}, "PledgesAndGrantsReceivable": {"BOY": "61670", "EOY": "61670"}, "AccountsReceivable": {"BOY": "57863", "EOY": "26694"}, "PrepaidExpensesDeferredCharges": {"BOY": "40153", "EOY": "5549"}, "LandBuildingsEquipmentBasis": "2526088", "LandBldgEquipmentAccumDeprec": "368403", "LandBuildingsEquipmentBasisNet": {"BOY": "2226861", "EOY": "2157685"}, "InvestmentsPubTradedSecurities": {"BOY": "27022", "EOY": "14591"}, "IntangibleAssets": {"EOY": "8493"}, "TotalAssets": {"BOY": "2450089", "EOY": "2364125"}, "AccountsPayableAccruedExpenses": {"BOY": "9832"}, "OtherLiabilities": {"BOY": "345843", "EOY": "347156"}, "TotalLiabilities": {"BOY": "355675", "EOY": "347156"}, "FollowSFAS117": "X", "UnrestrictedNetAssets": {"BOY": "2094414", "EOY": "2016969"}, "TotalNetAssetsFundBalances": {"BOY": "2094414", "EOY": "2016969"}, "TotalLiabNetAssetsFundBalances": {"BOY": "2450089", "EOY": "2364125"}, "ReconcilationRevenueExpenses": "-22688", "ReconcilationOtherChanges": "-54757", "MethodOfAccountingAccrual": "X", "AccountantCompileOrReview": "false", "FSAudited": "false", "FederalGrantAuditRequired": "false"}, "IRS990ScheduleA": {"@documentId": "RetDoc2", "PubliclySupportedOrg170b1Avi": "X", "GiftsGrantsContribReceived170": {"CurrentTaxYearMinus4Years": "640175", "CurrentTaxYearMinus3Years": "495836", "CurrentTaxYearMinus2Years": "508135", "CurrentTaxYearMinus1Year": "402984", "CurrentTaxYear": "107600", "Total": "2154730"}, "Total170": {"CurrentTaxYearMinus4Years": "640175", "CurrentTaxYearMinus3Years": "495836", "CurrentTaxYearMinus2Years": "508135", "CurrentTaxYearMinus1Year": "402984", "CurrentTaxYear": "107600", "Total": "2154730"}, "PublicSupportTotal170": "2154730", "GrossInvestmentIncome170": {"CurrentTaxYearMinus4Years": "5263", "CurrentTaxYearMinus3Years": "3602", "CurrentTaxYearMinus2Years": "2580", "CurrentTaxYearMinus1Year": "3803", "CurrentTaxYear": "648", "Total": "15896"}, "TotalSupport": "2170626", "GrossReceiptsFromAdmissionsEtc": "153499", "PublicSupportPertcentage170": "0.99270", "ThirtyThreePercntTestsCY170": "X"}, "IRS990ScheduleD": {"@documentId": "RetDoc3", "Land": {"OtherCostOrOtherBasis": "229348", "BookValue": "229348"}, "Buildings": {"OtherCostOrOtherBasis": "2125947", "Depreciation": "227632", "BookValue": "1898315"}, "Equipment": {"OtherCostOrOtherBasis": "170793", "Depreciation": "137478", "BookValue": "33315"}, "OtherLandBuildings": {"Depreciation": "3293", "BookValue": "-3293"}, "TotalOfBookValueLandBuildings": "2157685", "OtherLiabilities": {"Description": "YAMPA VALLEY BANK NOTE PAYABLE", "Amount": "347156"}, "TotalOfAmounts": "347156"}, "IRS990ScheduleO": {"@documentId": "RetDoc5", "GeneralExplanation": [{"Identifier": "ORGANIZATION'S PROCESS USED TO REVIEW FORM 990", "ReturnReference": "FORM 990, PAGE 6, PART VI, LINE 11B", "Explanation": "COPY OF FORM 990 IS PROVIDED TO BOARD MEMBERS FOR REVIEW AND COMMENTS."}, {"Identifier": "GOVERNING DOCUMENTS DISCLOSURE EXPLANATION", "ReturnReference": "FORM 990, PAGE 6, PART VI, LINE 19", "Explanation": "DOCUMENTS ARE MADE AVAILABLE TO THE PUBLIC UPON REQUEST."}, {"Identifier": "OTHER FEES FOR SERVICES", "ReturnReference": "FORM 990, PART IX, LINE 11G", "Explanation": "MEDICAL CONSULTANTS 95,922 0 0"}, {"Identifier": "OTHER CHANGES IN NET ASSETS EXPLANATION", "ReturnReference": "FORM 990, PART XI, LINE 9", "Explanation": "ADJ. ERRORS IN PRIOR YEARS (MATH ERRORS IN TOTALS) 54,757"}]}}}}