{"Return": {"@xmlns": "http://www.irs.gov/efile", "@xmlns:xsi": "http://www.w3.org/2001/XMLSchema-instance", "@returnVersion": "2010v3.2", "ReturnHeader": {"@binaryAttachmentCount": "0", "Timestamp": "2011-08-15T15:15:20-05:00", "TaxPeriodEndDate": "2010-12-31", "PreparerFirm": {"PreparerFirmBusinessName": {"BusinessNameLine1": "DJCK TAX CONSULTANTS LLC"}, "PreparerFirmUSAddress": {"AddressLine1": "108 N LAFAYETTE SUITE D PO BOX 6", "City": "GREENVILLE", "State": "MI", "ZIPCode": "488380605"}}, "ReturnType": "990EZ", "TaxPeriodBeginDate": "2010-01-01", "Filer": {"EIN": "208016914", "Name": {"BusinessNameLine1": "ALPHA FAMILY CENTER OF GREENVILLE"}, "NameControl": "ALPH", "Phone": "6162252265", "USAddress": {"AddressLine1": "117 E MONTCALM ST", "City": "GREENVILLE", "State": "MI", "ZIPCode": "48838"}}, "Officer": {"Name": "LAURA THOMPSON", "Title": "EXECUTIVE DIRECTOR", "Phone": "6162252265", "DateSigned": "2011-08-01", "AuthorizeThirdParty": "true"}, "Preparer": {"Name": "DOUGLAS SEYMOUR MST", "Phone": "6167548888", "DatePrepared": "2011-08-01"}, "TaxYear": "2010", "BuildTS": "2016-02-24 21:20:13Z"}, "ReturnData": {"@documentCount": "4", "IRS990EZ": {"@documentId": "RetDoc5", "@referenceDocumentId": "RetDoc4", "MethodOfAccountingAccrual": "X", "ScheduleBNotRequired": "X", "WebSite": "WWW.ALPHAFAMILYCENTER.ORG", "Organization501c3": {"@referenceDocumentId": "RetDoc3", "#text": "X"}, "GrossReceipts": "74954", "InfoInScheduleOPartI": "X", "ContributionsGiftsGrantsEtc": "54280", "ProgramServiceRevenue": "20674", "TotalRevenue": "74954", "GrantsAndSimilarAmountsPaid": "9548", "SalariesOtherCompEmplBenefits": "25331", "FeesAndOthPymtToIndContractors": "405", "OccupancyRentUtilitiesAndMaint": "18352", "PrintingPublicationsPostage": "1748", "OtherExpensesTotal": "13337", "TotalExpenses": "68721", "ExcessOrDeficitForYear": "6233", "NetAssetsOrFundBalancesBOY": "19070", "NetAssetsOrFundBalancesEOY": "25303", "InfoInScheduleOPartII": "X", "CashSavingsAndInvestments": {"BOY": "15239", "EOY": "23806"}, "OtherAssetsTotal": {"BOY": "6103", "EOY": "2120"}, "TotalAssets": {"BOY": "21342", "EOY": "25926"}, "SumOfTotalLiabilities": {"BOY": "2272", "EOY": "623"}, "NetAssetsOrFundBalances": {"BOY": "19070", "EOY": "25303"}, "InfoInScheduleOPartIII": "X", "PrimaryExemptPurpose": "AFFIRM FAMILY VALUES", "ProgramServiceAccomplishment": [{"DescriptionProgramServiceAccom": "AFFIRM AND PROMOTE THE SANCTITY OF HUMAN LIFE, THE VALUE OF THE FAMILY AND BIBLICAL SEXUALITY IN OUR COMMUNITY THROUGH DONATIONS OF GRANTS TO PURCHASE DIAPERS, FORMULA, BABY WIPES, SAFETY ITEMS, ETC...", "GrantsAndAllocations": "9548", "ProgramServiceExpenses": "9548"}, {"DescriptionProgramServiceAccom": "AFFIRM AND PROMOTE THE SANCTITY OF HUMAN LIFE, THE VALUE OF THE FAMILY AND BIBLICAL SEXUALITY IN OUR COMMUNITY THROUGH DONATIONS OF GRANTS TO PURCHASE DIAPERS, FORMULA, BABY WIPES, SAFETY ITEMS, ETC...", "ProgramServiceExpenses": "4717"}], "TotalProgramServiceExpenses": "14265", "OfficerDirectorTrusteeKeyEmpl": [{"PersonName": {"@referenceDocumentId": "RetDoc2", "#text": "BRUCE MARSMAN"}, "AddressUS": {"AddressLine1": "12605 STOUT", "City": "CEDAR SPRINGS", "State": "MI", "ZIPCode": "49319"}, "Title": "PRESIDENT", "AvgHoursPerWkDevotedToPosition": "1.00", "Compensation": "0"}, {"PersonName": {"@referenceDocumentId": "RetDoc2", "#text": "DR DAVE CRITTENDEN"}, "AddressUS": {"AddressLine1": "11604 SLAWSON LK RD", "City": "GREENVILLE", "State": "MI", "ZIPCode": "48838"}, "Title": "VICE PRESIDE", "AvgHoursPerWkDevotedToPosition": "1.00", "Compensation": "0"}, {"PersonName": {"@referenceDocumentId": "RetDoc2", "#text": "FAITH PRIESTER"}, "AddressUS": {"AddressLine1": "10870 LINCOLN LAKE AVE", "City": "GREENVILLE", "State": "MI", "ZIPCode": "48838"}, "Title": "SECRETARY", "AvgHoursPerWkDevotedToPosition": "1.50", "Compensation": "0"}, {"PersonName": {"@referenceDocumentId": "RetDoc2", "#text": "PHIL DUCHENY"}, "AddressUS": {"AddressLine1": "12165 PODUNK AVE", "City": "GREENVILLE", "State": "MI", "ZIPCode": "48838"}, "Title": "TREASURER", "AvgHoursPerWkDevotedToPosition": "1.00", "Compensation": "0"}, {"PersonName": {"@referenceDocumentId": "RetDoc2", "#text": "REV PAUL ARNOLD"}, "AddressUS": {"AddressLine1": "115 MCPHERSON", "City": "STANTON", "State": "MI", "ZIPCode": "48888"}, "Title": "DIRECTOR", "AvgHoursPerWkDevotedToPosition": "1.00", "Compensation": "0"}, {"PersonName": {"@referenceDocumentId": "RetDoc2", "#text": "JIM HOISINGTON"}, "AddressUS": {"AddressLine1": "4045 E SHORE DRIVE", "City": "STANTON", "State": "MI", "ZIPCode": "48888"}, "Title": "DIRECTOR", "AvgHoursPerWkDevotedToPosition": "1.00", "Compensation": "0"}, {"PersonName": {"@referenceDocumentId": "RetDoc2", "#text": "LAURA THOMPSON"}, "AddressUS": {"AddressLine1": "5199 W COLBY RD", "City": "SIDNEY", "State": "MI", "ZIPCode": "48885"}, "Title": "EXECUTIVE DI", "AvgHoursPerWkDevotedToPosition": "15.00", "Compensation": "10116"}], "ActivitiesNotPreviouslyRpt": "false", "MadeChangesToOrgnzngEtcDoc": "false", "OrganizationHadUBI": "false", "OrganizationDissolvedEtc": "false", "DidOrgFileForm1120POLThisYear": "false", "MadeLoansToFromOfficers": "false", "EngagedInExcessBenefitTrans": "false", "ProhibitedTaxShelterTrans": "false", "TheBooksAreInCareOf": {"NamePerson": "LAURA THOMPSON", "AddressUS": {"AddressLine1": "5199 W COLBY RD", "City": "SIDNEY", "State": "MI", "ZIPCode": "48885"}, "TelephoneNumber": "6162252265"}, "ForeignFinancialAccount": "false", "ForeignOffice": "false", "MaintainAnyDonorAdvisedFunds": "false", "DoesOrgHaveHospital": "false", "TanningServicesProvided": "false", "RelatedOrgControlledEntity": "false", "TransactionWithControlEntity": "false", "EngagePoliticalCmpgnActivities": "false", "EngageInLobbyingActivities": "false", "OperatingSchool": "false", "TrnsfrsExemptNonCharRelatedOrg": "false", "PartVIOfCompOfHighestPaidEmpl": "NONE", "PartVIAHghstPaidCntrctProfSer": "NONE", "FiledScheduleA": "true"}, "IRS990ScheduleA": {"@documentId": "RetDoc3", "PubliclySupportedOrg509a2": "X", "GiftsGrantsContribReceived509": {"CurrentTaxYear": "43276", "Total": "43276"}, "GrossReceiptsFromAdmissions": {"CurrentTaxYear": "20674", "Total": "20674"}, "Total509": {"CurrentTaxYear": "63950", "Total": "63950"}, "PublicSupportTotal509": "63950", "TotalSupportTotal": {"CurrentTaxYear": "63950", "Total": "63950"}, "PublicSupportPercentage509": "1.00000", "InvestmentIncomePercentage": "0.00000", "ThirtyThreePercntTestsCY509": "X"}, "IRS990ScheduleO": {"@documentId": "RetDoc4", "GeneralExplanation": [{"Identifier": "GRANTS AND SIMILAR AMTS PAID TO INDIVIDUALS", "ReturnReference": "FORM 990-EZ, PART I, LINE 10", "Explanation": "9,548 0 0"}, {"Identifier": "OTHER EXPENSES", "ReturnReference": "FORM 990-EZ, PART I, LINE 16", "Explanation": "LIFE WALK SUPPLIES 865 0 ANNUAL BANQUET SUPPLIES 135 0 STAMPING AND STITCHING SUPPLIES 155 0 CALENDAR SALES SUPPLIES 596 0 BABY BOTTLE BLESSINGS SUPPLIES 79 0 MISCELLANEOUS FUNDRAISING SUPPLIES 390 EXPENSES ADVERTISING AND PROMOTION 907 OFFICE SUPPLIES 1,604 INTERNET SERVICE 424 TELEPHONE 1,481 TRAVEL 815 CONFERENCES/MEETINGS 554 INSURANCE 1,812 BANK SERVICE CHARGES 34 DUES & SUBSCRIPTIONS 154 LICENSES & PERMITS 20 REPAIRS & MAINTENANCE 1,436 SUPPLIES 372 VOLUNTEER RECOGNITION 654 MISCELLANEOUS 850 TOTAL 13,337"}, {"Identifier": "OTHER ASSETS", "ReturnReference": "FORM 990-EZ, PART II, LINE 24", "Explanation": "INVENTORIES FOR SALE OR USE 3,606 322 COMPUTER AND PROJECTOR 2,184 2,184 LESS ACCUMULATED DEPRECIATION 437 1,136 750 750 TOTAL 6,103 2,120"}, {"Identifier": "OTHER LIABILITIES", "ReturnReference": "FORM 990-EZ, PART II, LINE 26", "Explanation": "PAYROLL TAX LIABILITIES 2,272 623"}, {"Identifier": "ALL OTHER ACHIEVEMENTS", "ReturnReference": "FORM 990-EZ, PART III, LINE 31", "Explanation": "AFFIRM AND PROMOTE THE SANCTITY OF HUMAN LIFE, THE VALUE OF THE FAMILY AND BIBLICAL SEXUALITY IN OUR COMMUNITY THROUGH DONATIONS OF GRANTS TO PURCHASE DIAPERS, FORMULA, BABY WIPES, SAFETY ITEMS, ETC..."}]}, "CompensationExplanation": {"@documentId": "RetDoc2", "Compensation": [{"PersonName": "BRUCE MARSMAN"}, {"PersonName": "DR DAVE CRITTENDEN"}, {"PersonName": "FAITH PRIESTER"}, {"PersonName": "PHIL DUCHENY"}, {"PersonName": "REV PAUL ARNOLD"}, {"PersonName": "JIM HOISINGTON"}, {"PersonName": "LAURA THOMPSON"}]}}}}