{"Return": {"@xmlns": "http://www.irs.gov/efile", "@xmlns:xsi": "http://www.w3.org/2001/XMLSchema-instance", "@returnVersion": "2010v3.2", "ReturnHeader": {"@binaryAttachmentCount": "0", "Timestamp": "2011-03-31T11:52:25-05:00", "TaxPeriodEndDate": "2010-12-31", "PreparerFirm": {"PreparerFirmBusinessName": {"BusinessNameLine1": "LINDSEY DAVIS & ASSOCIATES CPAS PA"}, "PreparerFirmUSAddress": {"AddressLine1": "PO BOX 146", "City": "RIPLEY", "State": "MS", "ZIPCode": "386630146"}}, "ReturnType": "990EZ", "TaxPeriodBeginDate": "2010-01-01", "Filer": {"EIN": "208196150", "Name": {"BusinessNameLine1": "SAV-A-LIFE PREGNANCY TESTING CENTER", "BusinessNameLine2": "OF RIPLEY INC"}, "NameControl": "SAV-", "Phone": "6628373295", "USAddress": {"AddressLine1": "PO BOX 1351", "City": "RIPLEY", "State": "MS", "ZIPCode": "38663"}}, "Officer": {"Name": "CHARLES DAVIS", "Title": "TREASURER", "Phone": "6628373295", "DateSigned": "2011-03-17"}, "Preparer": {"Name": "STEPHANIE CLIFTON", "Phone": "6628373295", "DatePrepared": "2011-03-17"}, "TaxYear": "2010", "BuildTS": "2016-02-24 21:20:13Z"}, "ReturnData": {"@documentCount": "4", "IRS990EZ": {"@documentId": "RetDoc4", "@referenceDocumentId": "RetDoc3", "MethodOfAccountingCash": "X", "ScheduleBNotRequired": "X", "WebSite": "N/A", "Organization501c3": {"@referenceDocumentId": "RetDoc2", "#text": "X"}, "GrossReceipts": "110324", "InfoInScheduleOPartI": "X", "ContributionsGiftsGrantsEtc": "107078", "OtherRevenueTotal": "3246", "TotalRevenue": "110324", "SalariesOtherCompEmplBenefits": "40459", "OtherExpensesTotal": "45652", "TotalExpenses": "86111", "ExcessOrDeficitForYear": "24213", "NetAssetsOrFundBalancesBOY": "38716", "NetAssetsOrFundBalancesEOY": "62929", "CashSavingsAndInvestments": {"BOY": "38716", "EOY": "62929"}, "TotalAssets": {"BOY": "38716", "EOY": "62929"}, "NetAssetsOrFundBalances": {"BOY": "38716", "EOY": "62929"}, "InfoInScheduleOPartIII": "X", "PrimaryExemptPurpose": "AN OUTREACH MINISTRY COMMITTED TO PRESENTING THE GOSPEL OF JESUS CHRIST TO WOMEN WITH CRISIS PREGNANCIES IN BOTH WORD AND DEED.", "ProgramServiceAccomplishment": {"DescriptionProgramServiceAccom": "TO FULLY EDUCATE CLIENTS ABOUT BOTH PRENATAL DEVEOPLMENT AND ABORTION AND ASSISTING WOMEN TO CARRY TO TERM BY PROVIDING EMOTIONAL SUPPORT AND PRACTICAL ASSISTANCE.", "ProgramServiceExpenses": "55954"}, "TotalProgramServiceExpenses": "55954", "OfficerDirectorTrusteeKeyEmpl": [{"PersonName": {"@referenceDocumentId": "RetDoc1", "#text": "MELISSA HARRISON"}, "AddressUS": {"AddressLine1": "114 EAST JEFFERSON", "City": "RIPLEY", "State": "MS", "ZIPCode": "38663"}, "Title": "BOARDMEMBER", "AvgHoursPerWkDevotedToPosition": "000.00", "Compensation": "0"}, {"PersonName": {"@referenceDocumentId": "RetDoc1", "#text": "BRO JASON HARMS"}, "AddressUS": {"AddressLine1": "114 FOREST GATE CIR", "City": "RIPLEY", "State": "MS", "ZIPCode": "38663"}, "Title": "BOARDMEMBER", "AvgHoursPerWkDevotedToPosition": "000.00", "Compensation": "0"}, {"PersonName": {"@referenceDocumentId": "RetDoc1", "#text": "CHARLES DAVIS"}, "AddressUS": {"AddressLine1": "9110 HIGHWAY 370", "City": "RIPLEY", "State": "MS", "ZIPCode": "38663"}, "Title": "TREASURER", "AvgHoursPerWkDevotedToPosition": "000.00", "Compensation": "0"}, {"PersonName": {"@referenceDocumentId": "RetDoc1", "#text": "AMY THOMAS"}, "AddressUS": {"AddressLine1": "4261 CR 301", "City": "WALNUT", "State": "MS", "ZIPCode": "38683"}, "Title": "SECRETARY", "AvgHoursPerWkDevotedToPosition": "000.00", "Compensation": "0"}, {"PersonName": {"@referenceDocumentId": "RetDoc1", "#text": "BRO JERRY BINGHAM"}, "AddressUS": {"AddressLine1": "HWY 15 S", "City": "RIPLEY", "State": "MS", "ZIPCode": "38663"}, "Title": "BOARDMEMBER", "AvgHoursPerWkDevotedToPosition": "000.00", "Compensation": "0"}, {"PersonName": {"@referenceDocumentId": "RetDoc1", "#text": "ROBERT DUNAVANT"}, "AddressUS": {"AddressLine1": "110 WINDRIDGE DR", "City": "RIPLEY", "State": "MS", "ZIPCode": "38663"}, "Title": "PRESIDENT", "AvgHoursPerWkDevotedToPosition": "000.00", "Compensation": "0"}, {"PersonName": {"@referenceDocumentId": "RetDoc1", "#text": "SIS KATE REGAN"}, "AddressUS": {"AddressLine1": "600 W 1ST ST", "City": "RIPLEY", "State": "MS", "ZIPCode": "38663"}, "Title": "BOARDMEMBER", "AvgHoursPerWkDevotedToPosition": "000.00", "Compensation": "0"}, {"PersonName": {"@referenceDocumentId": "RetDoc1", "#text": "TERRI STANFORD"}, "AddressUS": {"AddressLine1": "122 WINDRIDGE DR", "City": "RIPLEY", "State": "MS", "ZIPCode": "38663"}, "Title": "ASSISTANT DI", "AvgHoursPerWkDevotedToPosition": "35.00", "Compensation": "19789"}, {"PersonName": {"@referenceDocumentId": "RetDoc1", "#text": "LISA MASSENGILL"}, "AddressUS": {"AddressLine1": "111 FOREST GATE CIR", "City": "RIPLEY", "State": "MS", "ZIPCode": "38663"}, "Title": "BOARDMEMBER", "AvgHoursPerWkDevotedToPosition": "000.00", "Compensation": "0"}, {"PersonName": {"@referenceDocumentId": "RetDoc1", "#text": "FELESHA ROWLAND"}, "AddressUS": {"AddressLine1": "581 E WALNUT STREET", "City": "RIPLEY", "State": "MS", "ZIPCode": "38663"}, "Title": "DIRECTOR", "AvgHoursPerWkDevotedToPosition": "35.00", "Compensation": "17188"}, {"PersonName": {"@referenceDocumentId": "RetDoc1", "#text": "JERRY RENO"}, "AddressUS": {"AddressLine1": "406 W JEFFERSON STREET", "City": "RIPLEY", "State": "MS", "ZIPCode": "38663"}, "Title": "VICE-PRESIDE", "AvgHoursPerWkDevotedToPosition": "000.00", "Compensation": "0"}, {"PersonName": {"@referenceDocumentId": "RetDoc1", "#text": "TAJ COLOM"}, "AddressUS": {"AddressLine1": "621 CR 315", "City": "TIPLERSVILLE", "State": "MS", "ZIPCode": "38674"}, "Title": "BOARDMEMBER", "AvgHoursPerWkDevotedToPosition": "000.00", "Compensation": "0"}, {"PersonName": {"@referenceDocumentId": "RetDoc1", "#text": "ROGER CHILDS"}, "AddressUS": {"AddressLine1": "11700 CR 500", "City": "RIPLEY", "State": "MS", "ZIPCode": "38663"}, "Title": "BOARDMEMBER", "AvgHoursPerWkDevotedToPosition": "000.00", "Compensation": "0"}, {"PersonName": {"@referenceDocumentId": "RetDoc1", "#text": "MARTHA GOOLSBY"}, "AddressUS": {"AddressLine1": "112 NANCE STREET", "City": "RIPLEY", "State": "MS", "ZIPCode": "38663"}, "Title": "BOARDMEMBER", "AvgHoursPerWkDevotedToPosition": "000.00", "Compensation": "0"}, {"PersonName": {"@referenceDocumentId": "RetDoc1", "#text": "BRO ANTHONY MITCHELL"}, "AddressUS": {"AddressLine1": "155 LAKEVIEW DR", "City": "RIPLEY", "State": "MS", "ZIPCode": "38663"}, "Title": "BOARDMEMBER", "AvgHoursPerWkDevotedToPosition": "000.00", "Compensation": "0"}, {"PersonName": {"@referenceDocumentId": "RetDoc1", "#text": "VICKI SKINNER"}, "AddressUS": {"AddressLine1": "PO BOX 250", "City": "WALNUT", "State": "MS", "ZIPCode": "38683"}, "Title": "BOARDMEMBER", "AvgHoursPerWkDevotedToPosition": "000.00", "Compensation": "0"}], "ActivitiesNotPreviouslyRpt": "false", "MadeChangesToOrgnzngEtcDoc": "false", "OrganizationHadUBI": "false", "OrganizationDissolvedEtc": "false", "DidOrgFileForm1120POLThisYear": "false", "MadeLoansToFromOfficers": "false", "EngagedInExcessBenefitTrans": "false", "ProhibitedTaxShelterTrans": "false", "TheBooksAreInCareOf": {"NamePerson": "CHARLES DAVIS", "AddressUS": {"AddressLine1": "P O BOX 146", "City": "RIPLEY", "State": "MS", "ZIPCode": "38663"}, "TelephoneNumber": "6628373295"}, "ForeignFinancialAccount": "false", "ForeignOffice": "false", "MaintainAnyDonorAdvisedFunds": "false", "DoesOrgHaveHospital": "false", "TanningServicesProvided": "false", "RelatedOrgControlledEntity": "false", "TransactionWithControlEntity": "false", "EngagePoliticalCmpgnActivities": "false", "EngageInLobbyingActivities": "false", "OperatingSchool": "false", "TrnsfrsExemptNonCharRelatedOrg": "false", "PartVIOfCompOfHighestPaidEmpl": "NONE", "PartVIAHghstPaidCntrctProfSer": "NONE", "FiledScheduleA": "true"}, "IRS990ScheduleA": {"@documentId": "RetDoc2", "PubliclySupportedOrg509a2": "X", "GiftsGrantsContribReceived509": {"CurrentTaxYearMinus3Years": "59552", "CurrentTaxYearMinus2Years": "88106", "CurrentTaxYearMinus1Year": "133047", "CurrentTaxYear": "107078", "Total": "387783"}, "GrossReceiptsFromAdmissions": {"CurrentTaxYearMinus1Year": "27000", "CurrentTaxYear": "3246", "Total": "30246"}, "Total509": {"CurrentTaxYearMinus3Years": "59552", "CurrentTaxYearMinus2Years": "88106", "CurrentTaxYearMinus1Year": "160047", "CurrentTaxYear": "110324", "Total": "418029"}, "PublicSupportTotal509": "418029", "TotalSupportTotal": {"CurrentTaxYearMinus3Years": "59552", "CurrentTaxYearMinus2Years": "88106", "CurrentTaxYearMinus1Year": "160047", "CurrentTaxYear": "110324", "Total": "418029"}, "PublicSupportPercentage509": "1.00000", "PriorYearSupportPercentage": "1.00000", "InvestmentIncomePercentage": "0.00000", "ThirtyThreePercntTestsCY509": "X"}, "IRS990ScheduleO": {"@documentId": "RetDoc3", "GeneralExplanation": [{"Identifier": "OTHER REVENUE", "ReturnReference": "FORM 990-EZ, PART I, LINE 8", "Explanation": "T-SHIRT SALES 3,246 TOTAL 3,246"}, {"Identifier": "OTHER EXPENSES", "ReturnReference": "FORM 990-EZ, PART I, LINE 16", "Explanation": "EXPENSES 1,149 973 EDUCATIONAL MATERIALS 3,089 COUNSELOR TRAINING 778 FLOWERS & GIFTS 11 FUNDRAISING EXPENSES 2,339 BANQUET EXPENSES 8,906 5-K RUN EXPENSES 2,439 REPAIRS & MAINTENANCE 2,131 INSURANCE 2,868 KITCHEN SUPPLIES 45 OFFICE SUPPLIES 1,206 UTILITIES 2,134 TELEPHONE 1,631 POSTAGE 621 SUPPLIES 744 AFFILIATION FEES 200 NEWSLETTER 2,937 PRINTING/COPIER EXPENSE 1,439 STATE REGISTRATION FEES 50 BUILDING EXPENSE 8,199 FURNITURE EXPENSE 456 MISCELLANEOUS 1,307 TOTAL 45,652"}, {"Identifier": "PRIMARY EXEMPT PURPOSE", "ReturnReference": "FORM 990-EZ, PART III", "Explanation": "AN OUTREACH MINISTRY COMMITTED TO PRESENTING THE GOSPEL OF JESUS CHRIST TO WOMEN WITH CRISIS PREGNANCIES IN BOTH WORD AND DEED."}]}, "CompensationExplanation": {"@documentId": "RetDoc1", "Compensation": [{"PersonName": "MELISSA HARRISON"}, {"PersonName": "BRO JASON HARMS"}, {"PersonName": "CHARLES DAVIS"}, {"PersonName": "AMY THOMAS"}, {"PersonName": "BRO JERRY BINGHAM"}, {"PersonName": "ROBERT DUNAVANT"}, {"PersonName": "SIS KATE REGAN"}, {"PersonName": "TERRI STANFORD"}, {"PersonName": "LISA MASSENGILL"}, {"PersonName": "FELESHA ROWLAND"}, {"PersonName": "JERRY RENO"}, {"PersonName": "TAJ COLOM"}, {"PersonName": "ROGER CHILDS"}, {"PersonName": "MARTHA GOOLSBY"}, {"PersonName": "BRO ANTHONY MITCHELL"}, {"PersonName": "VICKI SKINNER"}]}}}}