{"Return": {"@xmlns": "http://www.irs.gov/efile", "@returnVersion": "2010v3.2", "ReturnHeader": {"@binaryAttachmentCount": "0", "Timestamp": "2011-06-01T14:27:37-05:00", "TaxPeriodEndDate": "2010-12-31", "PreparerFirm": {"PreparerFirmBusinessName": {"BusinessNameLine1": "BOHL ASSOCIATES INC"}, "PreparerFirmUSAddress": {"AddressLine1": "515 EAST LASALLE AVENUE", "City": "BARRON", "State": "WI", "ZIPCode": "54812"}}, "ReturnType": "990EZ", "TaxPeriodBeginDate": "2010-01-01", "Filer": {"EIN": "391981730", "Name": {"BusinessNameLine1": "PREGNANCY HELP CENTER OF RICE LAKE"}, "NameControl": "PREG", "USAddress": {"AddressLine1": "PO BOX 334", "City": "RICE LAKE", "State": "WI", "ZIPCode": "54868"}}, "Officer": {"Name": "STEVEN SVENDSEN", "Title": "TREASURER", "Phone": "7157364357", "DateSigned": "2011-05-11", "AuthorizeThirdParty": "false"}, "Preparer": {"Name": "Mary A Bohl", "Phone": "7155373119", "DatePrepared": "2011-06-01"}, "TaxYear": "2010", "BuildTS": "2016-02-24 21:20:13Z"}, "ReturnData": {"@documentCount": "4", "IRS990EZ": {"@documentId": "990EZ", "MethodOfAccountingCash": "X", "ScheduleBNotRequired": "X", "Organization501c3": {"@referenceDocumentId": "990A", "#text": "X"}, "GrossReceipts": "65881", "InfoInScheduleOPartI": "X", "ContributionsGiftsGrantsEtc": "29848", "InvestmentIncome": "296", "FundraisingGrossIncome": "35737", "SpecialEventsNetIncomeLoss": "35737", "TotalRevenue": "65881", "SalariesOtherCompEmplBenefits": "21793", "OccupancyRentUtilitiesAndMaint": "12240", "PrintingPublicationsPostage": "5243", "OtherExpensesTotal": "14996", "TotalExpenses": "54272", "ExcessOrDeficitForYear": "11609", "NetAssetsOrFundBalancesBOY": "32999", "NetAssetsOrFundBalancesEOY": "44608", "InfoInScheduleOPartII": "X", "CashSavingsAndInvestments": {"BOY": "26943", "EOY": "24453"}, "LandAndBuildings": {"BOY": "0", "EOY": "70501"}, "OtherAssetsTotal": {"BOY": "6056", "EOY": "5654"}, "TotalAssets": {"BOY": "32999", "EOY": "100608"}, "SumOfTotalLiabilities": {"BOY": "0", "EOY": "56000"}, "NetAssetsOrFundBalances": {"BOY": "32999", "EOY": "44608"}, "PrimaryExemptPurpose": "ASSIST WITH UNPLANNED PREGNANCIES", "ProgramServiceAccomplishment": {"DescriptionProgramServiceAccom": "ASSIST WOMEN AND FAMILIES IN AN UNPLANNED PREGNANCY BY ENCOURAGING ALTERNATIVES TO ABORTION AND MINISTER TO PHYSICAL AND SPIRITUAL NEEDS", "ProgramServiceExpenses": "0"}, "TotalProgramServiceExpenses": "0", "OfficerDirectorTrusteeKeyEmpl": [{"PersonName": "KAREN SCHAUF", "AddressUS": {"AddressLine1": "1659 10 12 STREET", "City": "BARRON", "State": "WI", "ZIPCode": "54812"}, "Title": "CHAIRPERSON", "AvgHoursPerWkDevotedToPosition": "1", "Compensation": "0", "ContriToEmplBenefitPlansEtc": "0", "ExpenseAccountOtherAllowances": "0"}, {"PersonName": "JEANINE SOLUM", "AddressUS": {"AddressLine1": "304 WEST HUMBIRD STREET", "City": "RICE LAKE", "State": "WI", "ZIPCode": "54868"}, "Title": "SECRETARY", "AvgHoursPerWkDevotedToPosition": "0", "Compensation": "0", "ContriToEmplBenefitPlansEtc": "0", "ExpenseAccountOtherAllowances": "0"}, {"PersonName": "PAUL POPPE", "AddressUS": {"AddressLine1": "1325 WOODLAND AVE", "City": "BARRON", "State": "WI", "ZIPCode": "54812"}, "Title": "DIRECTOR", "AvgHoursPerWkDevotedToPosition": "0", "Compensation": "0", "ContriToEmplBenefitPlansEtc": "0", "ExpenseAccountOtherAllowances": "0"}, {"PersonName": "STEVEN SVENDSEN", "AddressUS": {"AddressLine1": "2046 16 12 AVE", "City": "CAMERON", "State": "WI", "ZIPCode": "54822"}, "Title": "TREASURER", "AvgHoursPerWkDevotedToPosition": "0", "Compensation": "0", "ContriToEmplBenefitPlansEtc": "0", "ExpenseAccountOtherAllowances": "0"}, {"PersonName": "LOIS WRIGHT", "AddressUS": {"AddressLine1": "2740 10TH STREET", "City": "BARRONETT", "State": "WI", "ZIPCode": "54813"}, "Title": "DIRECTOR", "AvgHoursPerWkDevotedToPosition": "0", "Compensation": "0", "ContriToEmplBenefitPlansEtc": "0", "ExpenseAccountOtherAllowances": "0"}], "ActivitiesNotPreviouslyRpt": "false", "MadeChangesToOrgnzngEtcDoc": "false", "OrganizationHadUBI": "false", "OrganizationDissolvedEtc": "false", "MadeLoansToFromOfficers": "false", "EngagedInExcessBenefitTrans": "false", "TheBooksAreInCareOf": {"NamePerson": "STEVEN SVENDSEN", "AddressUS": {"AddressLine1": "2046 16 12 AVE", "City": "CAMERON", "State": "WI", "ZIPCode": "54822"}, "TelephoneNumber": "7157364357"}, "MaintainAnyDonorAdvisedFunds": "false", "DoesOrgHaveHospital": "false", "TanningServicesProvided": "false", "RelatedOrgControlledEntity": "false", "TransactionWithControlEntity": "false", "EngagePoliticalCmpgnActivities": "false", "EngageInLobbyingActivities": "false", "OperatingSchool": {"@referenceDocumentId": "990E", "#text": "false"}, "TrnsfrsExemptNonCharRelatedOrg": "false", "PartVIOfCompOfHighestPaidEmpl": "NONE", "PartVIAHghstPaidCntrctProfSer": "NONE", "FiledScheduleA": "true"}, "IRS990ScheduleA": {"@documentId": "990A", "PubliclySupportedOrg509a2": "X", "GiftsGrantsContribReceived509": {"CurrentTaxYearMinus4Years": "20034", "CurrentTaxYearMinus3Years": "24297", "CurrentTaxYearMinus2Years": "27092", "CurrentTaxYearMinus1Year": "28303", "CurrentTaxYear": "29848", "Total": "129574"}, "GrossReceiptsFromAdmissions": {"CurrentTaxYearMinus4Years": "33231", "CurrentTaxYearMinus3Years": "24173", "CurrentTaxYearMinus2Years": "29208", "CurrentTaxYearMinus1Year": "28401", "CurrentTaxYear": "35737", "Total": "150750"}, "Total509": {"CurrentTaxYearMinus4Years": "53265", "CurrentTaxYearMinus3Years": "48470", "CurrentTaxYearMinus2Years": "56300", "CurrentTaxYearMinus1Year": "56704", "CurrentTaxYear": "65585", "Total": "280324"}, "PublicSupportTotal509": "280324", "GrossInvestmentIncome509": {"CurrentTaxYearMinus4Years": "352", "CurrentTaxYearMinus3Years": "608", "CurrentTaxYearMinus2Years": "479", "CurrentTaxYearMinus1Year": "237", "CurrentTaxYear": "296", "Total": "1972"}, "InvestmentIncomeAndUBTI": {"CurrentTaxYearMinus4Years": "352", "CurrentTaxYearMinus3Years": "608", "CurrentTaxYearMinus2Years": "479", "CurrentTaxYearMinus1Year": "237", "CurrentTaxYear": "296", "Total": "1972"}, "TotalSupportTotal": {"CurrentTaxYearMinus4Years": "53617", "CurrentTaxYearMinus3Years": "49078", "CurrentTaxYearMinus2Years": "56779", "CurrentTaxYearMinus1Year": "56941", "CurrentTaxYear": "65881", "Total": "282296"}, "PublicSupportPercentage509": "0.99300", "PriorYearSupportPercentage": "0.99250", "InvestmentIncomePercentage": "0.00700", "PriorYrInvestIncomePercentage": "0.00750", "ThirtyThreePercntTestsCY509": "X"}, "IRS990ScheduleG": {"@documentId": "990G", "EventsInformation": {"NameOfEvent1": "CHG FOR LIFE", "GrossReceiptsEvent1": "17639", "GrossRevenueEvent1": "17639", "NameOfEvent2": "BIKE FOR LIF", "GrossReceiptsEvent2": "17139", "GrossRevenueEvent2": "17139", "TotalNumberOfOtherEvents": "3", "GrossReceiptsOtherEvents": "959", "GrossRevenueOtherEvents": "959", "GrossReceiptsTotal": "35737", "GrossRevenueTotalEvents": "35737", "NetIncomeSummary": "35737"}}, "IRS990ScheduleO": {"@documentId": "990O", "GeneralExplanation": [{"Identifier": "01. Description of other expenses (Part I, line 16)", "Explanation": "DESCRIPTION AMOUNT OFFICE AND ADMINISTRATION 6737 MINISTRY PROGRAM 416 SUPPORT SERVICES 65 DEPRECIATION 276 MINISTRY ALLOWANCES 2616 FUNDRAISERS 3219 PAYROLL TAX 1667"}, {"Identifier": "02. Description of other assets (Part II, line 24)", "Explanation": "BEGINNING CATEGORY OF YEAR END OF YEAR OFFICE EQUIP AND REMODELING 6056 5654"}, {"Identifier": "03. Description of total liabilities (Part II, line 26)", "Explanation": "BEGINNING CATEGORY OF YEAR END OF YEAR PAYROLL LIABILITIES 0 0 NOTE PAYABLE BANK 0 56000"}]}}}}